sentient_agent_framework/__init__.py
sentient_agent_framework/implementation/__init__.py
sentient_agent_framework/implementation/default_hook.py
sentient_agent_framework/implementation/default_response_handler.py
sentient_agent_framework/implementation/default_text_stream.py
sentient_agent_framework/implementation/id_generator.py
sentient_agent_framework/interface/__init__.py
sentient_agent_framework/interface/events.py
sentient_agent_framework/interface/exceptions.py
sentient_agent_framework/interface/hook.py
sentient_agent_framework/interface/identity.py
sentient_agent_framework/interface/response_handler.py
sentient_agent_framework/interface/stream_event_emitter.py
sentient_agent_framework-0.1.1.dist-info/licenses/LICENSE
sentient_agent_framework-0.1.1.dist-info/METADATA
sentient_agent_framework-0.1.1.dist-info/WHEEL
sentient_agent_framework-0.1.1.dist-info/top_level.txt
sentient_agent_framework-0.1.1.dist-info/RECORD
