Metadata-Version: 2.4
Name: sentient-agent-framework
Version: 0.1.1
Summary: This python package provides an agent framework that can be used to build agents that serve Sentient Chat events.
Author-email: Chris Aubin <christopher@sentient.xyz>
Maintainer-email: Chris Aubin <christopher@sentient.xyz>
License-Expression: Apache-2.0
Project-URL: Homepage, https://github.com/sentient-agi/Sentient-Agent-Framework
Project-URL: Issues, https://github.com/sentient-agi/Sentient-Agent-Framework/issues
Project-URL: Website, https://sentient.xyz
Classifier: Development Status :: 4 - Beta
Classifier: Intended Audience :: Developers
Classifier: Programming Language :: Python :: 3.9
Requires-Python: >=3.9
License-File: LICENSE
Dynamic: license-file
